baseband/__init__.py
baseband/_astropy_init.py
baseband/conftest.py
baseband/version.py
baseband/base/__init__.py
baseband/base/base.py
baseband/base/encoding.py
baseband/base/file_info.py
baseband/base/frame.py
baseband/base/header.py
baseband/base/offsets.py
baseband/base/payload.py
baseband/base/utils.py
baseband/base/tests/__init__.py
baseband/base/tests/test_base.py
baseband/base/tests/test_file_info.py
baseband/base/tests/test_header_parser.py
baseband/base/tests/test_offsets.py
baseband/base/tests/test_opener.py
baseband/base/tests/test_utils.py
baseband/dada/__init__.py
baseband/dada/base.py
baseband/dada/frame.py
baseband/dada/header.py
baseband/dada/payload.py
baseband/dada/tests/__init__.py
baseband/dada/tests/test_dada.py
baseband/data/README.rst
baseband/data/__init__.py
baseband/data/sample.dada
baseband/data/sample.m4
baseband/data/sample.m5b
baseband/data/sample.vdif
baseband/data/sample_16track.m4
baseband/data/sample_32track.m4
baseband/data/sample_32track_fanout2.m4
baseband/data/sample_64track_fanout2_ft.m4
baseband/data/sample_arochime.vdif
baseband/data/sample_bps1.vdif
baseband/data/sample_drao_corrupted.vdif
baseband/data/sample_meerkat.dada
baseband/data/sample_mwa.vdif
baseband/data/sample_puppi.raw
baseband/data/sample_vegas.raw
baseband/data/sample_vlbi.vdif
baseband/data/gsb/__init__.py
baseband/data/gsb/sample_gsb_phased.Pol-L1.dat
baseband/data/gsb/sample_gsb_phased.Pol-L2.dat
baseband/data/gsb/sample_gsb_phased.Pol-R1.dat
baseband/data/gsb/sample_gsb_phased.Pol-R2.dat
baseband/data/gsb/sample_gsb_phased.timestamp
baseband/data/gsb/sample_gsb_rawdump.dat
baseband/data/gsb/sample_gsb_rawdump.timestamp
baseband/gsb/__init__.py
baseband/gsb/base.py
baseband/gsb/file_info.py
baseband/gsb/frame.py
baseband/gsb/header.py
baseband/gsb/payload.py
baseband/gsb/tests/__init__.py
baseband/gsb/tests/test_gsb.py
baseband/guppi/__init__.py
baseband/guppi/base.py
baseband/guppi/file_info.py
baseband/guppi/frame.py
baseband/guppi/header.py
baseband-4.2.0.dist-info/LICENSE
baseband-4.2.0.dist-info/METADATA
baseband-4.2.0.dist-info/WHEEL
baseband-4.2.0.dist-info/entry_points.txt
baseband-4.2.0.dist-info/top_level.txt
baseband-4.2.0.dist-info/RECORD
