Metadata-Version: 2.1
Name: baseband
Version: 4.2.0
Summary: A package for radio baseband I/O
Home-page: https://github.com/mhvk/baseband
Author: Marten H. van Kerkwijk, Chenchong Zhu
Author-email: mhvk@astro.utoronto.ca
License: GNU GPL v3+
Project-URL: Documentation, https://baseband.readthedocs.io
Project-URL: Source, https://github.com/mhvk/baseband
Requires-Python: >=3.10
License-File: LICENSE
Requires-Dist: astropy >=5.1
Provides-Extra: all
Requires-Dist: baseband-tasks[all] ; extra == 'all'
Provides-Extra: cov
Requires-Dist: pytest-cov ; extra == 'cov'
Provides-Extra: docs
Requires-Dist: sphinx-astropy ; extra == 'docs'
Provides-Extra: test
Requires-Dist: pytest-astropy-header ; extra == 'test'
Requires-Dist: pytest-doctestplus ; extra == 'test'
Requires-Dist: pytest-filter-subpackage ; extra == 'test'
Requires-Dist: pytest-remotedata ; extra == 'test'
